[
  {
    "turn_number": 1,
    "result": "",
    "news": "아이스크림 트럭에서 깜짝 놀랄 만한 '무지개맛 아이스크림'을 만들 거라는 소문이 돌고 있어요! 성공하면 대박일까요?",
    "news_tag": "mid",
    "stocks": [
      {
        "name": "퓨전 타코 트럭",
        "expectation": "큰 영향이 없을 거예요."
      },
      {
        "name": "아이스크림 트럭",
        "expectation": "소문대로 특별한 맛이 나오면 인기가 아주 많아질 수 있어요. 하지만 맛없으면 실망해서 손님이 줄 수도 있어요."
      },
      {
        "name": "샌드위치 트럭",
        "expectation": "큰 영향이 없을 거예요."
      }
    ]
  },
  {
    "turn_number": 2,
    "result": "",
    "news": "갑자기 날씨가 아주아주 더워졌어요! 햇볕이 쨍쨍해서 밖에 있기 힘들 정도예요.",
    "news_tag": "all",
    "stocks": [
      {
        "name": "퓨전 타코 트럭",
        "expectation": "너무 더운 날씨 때문에 시원한 음식을 찾는 손님이 늘어나거나, 너무 더워서 밖에 잘 나오지 않을 수도 있어요."
      },
      {
        "name": "아이스크림 트럭",
        "expectation": "너무 더운 날씨 때문에 시원한 음식을 찾는 손님이 늘어나거나, 너무 더워서 밖에 잘 나오지 않을 수도 있어요."
      },
      {
        "name": "샌드위치 트럭",
        "expectation": "너무 더운 날씨 때문에 시원한 음식을 찾는 손님이 늘어나거나, 너무 더워서 밖에 잘 나오지 않을 수도 있어요."
      }
    ]
  },
  {
    "turn_number": 3,
    "result": "",
    "news": "유명한 어린이 맛집 유튜버 '맛탐정 꼬마'가 퓨전 타코 트럭을 방문할 수도 있다는 소문이 돌고 있어요! 정말로 올까요?",
    "news_tag": "high",
    "stocks": [
      {
        "name": "퓨전 타코 트럭",
        "expectation": "유튜버가 오면 인기가 엄청나게 올라갈 수 있어요. 하지만 안 오면 기대했던 손님들이 실망할 수도 있어요."
      },
      {
        "name": "아이스크림 트럭",
        "expectation": "큰 영향이 없을 거예요."
      },
      {
        "name": "샌드위치 트럭",
        "expectation": "큰 영향이 없을 거예요."
      }
    ]
  },
  {
    "turn_number": 4,
    "result": "",
    "news": "아이스크림 트럭에 아주 귀한 '반짝이 설탕' 재료가 들어올지도 모른대요. 이걸로 만들면 더 특별한 아이스크림이 될까요?",
    "news_tag": "mid",
    "stocks": [
      {
        "name": "퓨전 타코 트럭",
        "expectation": "큰 영향이 없을 거예요."
      },
      {
        "name": "아이스크림 트럭",
        "expectation": "특별한 재료가 들어오면 인기가 더 많아질 수 있어요. 하지만 재료를 못 구하면 실망하는 손님이 생길 수도 있어요."
      },
      {
        "name": "샌드위치 트럭",
        "expectation": "큰 영향이 없을 거예요."
      }
    ]
  },
  {
    "turn_number": 5,
    "result": "",
    "news": "마을에 '신나는 숨바꼭질 보물찾기 대회'가 갑자기 열렸어요! 많은 친구들이 마을 곳곳을 찾아다니고 있대요.",
    "news_tag": "all",
    "stocks": [
      {
        "name": "퓨전 타코 트럭",
        "expectation": "마을에 친구들이 많이 모여들어서 손님이 늘어날 수도 있고, 보물찾기에 집중해서 음식을 안 사 먹을 수도 있어요."
      },
      {
        "name": "아이스크림 트럭",
        "expectation": "마을에 친구들이 많이 모여들어서 손님이 늘어날 수도 있고, 보물찾기에 집중해서 음식을 안 사 먹을 수도 있어요."
      },
      {
        "name": "샌드위치 트럭",
        "expectation": "마을에 친구들이 많이 모여들어서 손님이 늘어날 수도 있고, 보물찾기에 집중해서 음식을 안 사 먹을 수도 있어요."
      }
    ]
  },
  {
    "turn_number": 6,
    "result": "",
    "news": "퓨전 타코 트럭이 '우주 최강 매운맛 타코 챌린지'를 시작할 거라는 소문이 돌고 있어요! 용감한 친구들이 도전할까요?",
    "news_tag": "high",
    "stocks": [
      {
        "name": "퓨전 타코 트럭",
        "expectation": "매운맛 챌린지가 성공하면 소문이 나서 손님이 몰릴 수 있어요. 하지만 너무 매워서 아무도 안 오면 손님이 줄 수도 있어요."
      },
      {
        "name": "아이스크림 트럭",
        "expectation": "큰 영향이 없을 거예요."
      },
      {
        "name": "샌드위치 트럭",
        "expectation": "큰 영향이 없을 거예요."
      }
    ]
  },
  {
    "turn_number": 7,
    "result": "",
    "news": "",
    "news_tag": "",
    "stocks": [
      {
        "name": "퓨전 타코 트럭",
        "expectation": ""
      },
      {
        "name": "아이스크림 트럭",
        "expectation": ""
      },
      {
        "name": "샌드위치 트럭",
        "expectation": ""
      }
    ]
  }
]